panel_neuroglancer/__init__.py
panel_neuroglancer/neuroglancer.py
panel_neuroglancer/.ipynb_checkpoints/__init__-checkpoint.py
panel_neuroglancer/.ipynb_checkpoints/neuroglancer_nb-checkpoint.py
panel_neuroglancer-0.1.0.dist-info/METADATA
panel_neuroglancer-0.1.0.dist-info/WHEEL
panel_neuroglancer-0.1.0.dist-info/licenses/LICENSE
panel_neuroglancer-0.1.0.dist-info/RECORD
