Metadata-Version: 2.1
Name: panel-neuroglancer
Version: 0.1.0
Summary: Add your description here
Requires-Python: >=3.10
License-File: LICENSE
Requires-Dist: neuroglancer>=2.40.1
Requires-Dist: panel>=1.5.4
